setup.py
mozb2g/__init__.py
mozb2g/b2gmixin.py
mozb2g.egg-info/PKG-INFO
mozb2g.egg-info/SOURCES.txt
mozb2g.egg-info/dependency_links.txt
mozb2g.egg-info/not-zip-safe
mozb2g.egg-info/requires.txt
mozb2g.egg-info/top_level.txt