Metadata-Version: 1.0
Name: mozb2g
Version: 0.3
Summary: B2G specific code for device automation
Home-page: https://wiki.mozilla.org/Auto-tools/Projects/Mozbase
Author: Mozilla Automation and Testing Team
Author-email: tools@lists.mozilla.org
License: MPL
Platform: UNKNOWN
